timeme/__init__.py
timeme/timer.py
timeme/timer_utils.py
Please_TimeMe-0.0.1.dist-info/LICENSE.txt
Please_TimeMe-0.0.1.dist-info/METADATA
Please_TimeMe-0.0.1.dist-info/WHEEL
Please_TimeMe-0.0.1.dist-info/top_level.txt
Please_TimeMe-0.0.1.dist-info/RECORD
