Metadata-Version: 2.1
Name: Please-TimeMe
Version: 0.0.1
Summary: A small package to help
Author: Rohin Dasari
Author-email: Rohin Dasari <rohin.dasari@gmail.com>
License: MIT License        
Project-URL: Homepage, https://github.com/rohin-dasari/TimeMe
Keywords: profile,timing,runtime
Classifier: License :: OSI Approved :: MIT License
Classifier: Programming Language :: Python :: 3
Classifier: Topic :: Scientific/Engineering
Classifier: Topic :: Software Development
Requires-Python: >=3.6
License-File: LICENSE.txt
Requires-Dist: pandas
Requires-Dist: tqdm
